neuronetlearn/__init__.py
neuronetlearn/genSetting.py
neuronetlearn/getBIC.py
neuronetlearn/ht.py
neuronetlearn/net_est_auto.py
neuronetlearn/net_inf.py
neuronetlearn/net_inf_threshold.py
neuronetlearn/simu_net.py
neuronetlearn/spg_genlasso_solver_jit.py
neuronetlearn/util.py
neuronetlearn-1.0.0.dist-info/LICENSE
neuronetlearn-1.0.0.dist-info/METADATA
neuronetlearn-1.0.0.dist-info/WHEEL
neuronetlearn-1.0.0.dist-info/top_level.txt
neuronetlearn-1.0.0.dist-info/RECORD
