Metadata-Version: 2.1
Name: neuronetlearn
Version: 1.0.0
Summary: Multi-Experiment Network Estimation and Inference for High-Dimensional Point Process Data
Home-page: https://github.com/stevenwang/NeuroNetLearn
Author: Xu Wang
Author-email: wangxu85@uw.edu
License: UNKNOWN
Project-URL: Bug Tracker, https://github.com/stevenwang/NeuroNetLearn/issues
Platform: UNKNOWN
Classifier: Programming Language :: Python :: 3
Classifier: License :: Other/Proprietary License
Classifier: Operating System :: OS Independent
Requires-Python: >=3.6
License-File: LICENSE
